yaxit/__init__.py
yaxit/cli.py
yaxit/integrations/bluice.py
yaxit/integrations/xephyr.py
yaxit/integrations/zfit.py
yaxit/plotting.py
yaxit/rest.py
yaxit/settings.py
yaxit/utils.py
yaxit/xarray.py
yaxit/yaxit.py
yaxit-0.1.0.dist-info/entry_points.txt
yaxit-0.1.0.dist-info/LICENSE
yaxit-0.1.0.dist-info/WHEEL
yaxit-0.1.0.dist-info/METADATA
yaxit-0.1.0.dist-info/RECORD
